benchformer/__init__.py
benchformer/configs/__init__.py
benchformer/configs/fnet/FNetForPARus.json
benchformer/configs/fnet/__init__.py
benchformer/configs/fnet/configs.json
benchformer/data/__init__.py
benchformer/data/processors/GlueTaskProcessor.py
benchformer/data/processors/Processor.py
benchformer/data/processors/ProcessorBuilder.py
benchformer/data/processors/TransformerProcessor.py
benchformer/data/processors/__init__.py
benchformer/glue/GlueTaskModel.py
benchformer/glue/TaskModelBuilder.py
benchformer/glue/__init__.py
benchformer/models/Model.py
benchformer/models/ModelBuilder.py
benchformer/models/TransformerModel.py
benchformer/models/__init__.py
benchformer/models/fnet/FNet.py
benchformer/models/fnet/TaskFNet.py
benchformer/models/fnet/__init__.py
benchformer-0.0.1.dev1.dist-info/LICENSE
benchformer-0.0.1.dev1.dist-info/METADATA
benchformer-0.0.1.dev1.dist-info/WHEEL
benchformer-0.0.1.dev1.dist-info/top_level.txt
benchformer-0.0.1.dev1.dist-info/RECORD
