Metadata-Version: 2.1
Name: benchformer
Version: 0.0.1.dev1
Summary: Transformers Language Models benchmarking tool
Home-page: https://github.com/serafima-ai/BenchFormer
Author: Nikita Syromiatnikov
Author-email: nik@serafima.ai
License: UNKNOWN
Project-URL: Bug Tracker, https://github.com/serafima-ai/BenchFormer/issues
Project-URL: Source Code, https://github.com/serafima-ai/BenchFormer
Platform: UNKNOWN
Classifier: Development Status :: 2 - Pre-Alpha
Classifier: Intended Audience :: Developers
Classifier: Intended Audience :: Education
Classifier: Intended Audience :: Science/Research
Classifier: Programming Language :: Python :: 3
Classifier: Programming Language :: Python :: 3.6
Classifier: License :: OSI Approved :: Apache Software License
Classifier: Operating System :: OS Independent
Classifier: Topic :: Scientific/Engineering :: Artificial Intelligence
Requires-Python: >=3.6
License-File: LICENSE
Requires-Dist: dotmap (>=1.3.13)
Requires-Dist: scipy (>=1.4.1)
Requires-Dist: pandas (>=0.25.3)
Requires-Dist: torch (>=1.10.1)
Requires-Dist: pytorch-lightning (==0.7.1)
Requires-Dist: transformers (==4.12.3)
